fxq/ae/agent/__init__.py
fxq/ae/agent/cli.py
fxq/ae/agent/constants.py
fxq/ae/agent/fxq_ae_agent_app.py
fxq/ae/agent/wsgi.py
fxq/ae/agent/callback/__init__.py
fxq/ae/agent/callback/handler.py
fxq/ae/agent/factory/__init__.py
fxq/ae/agent/factory/run.py
fxq/ae/agent/model/__init__.py
fxq/ae/agent/model/job.py
fxq/ae/agent/model/run.py
fxq/ae/agent/model/status.py
fxq/ae/agent/service/__init__.py
fxq/ae/agent/service/consul.py
fxq/ae/agent/service/docker.py
fxq/ae/agent/service/job.py
fxq/ae/agent/service/run.py
fxq_ae_agent-0.0.16.dist-info/METADATA
fxq_ae_agent-0.0.16.dist-info/WHEEL
fxq_ae_agent-0.0.16.dist-info/entry_points.txt
fxq_ae_agent-0.0.16.dist-info/top_level.txt
fxq_ae_agent-0.0.16.dist-info/RECORD
