Metadata-Version: 2.1
Name: fxq-ae-agent
Version: 0.0.16
Summary: Analytics Engine Agent Client, Provisions and executes docker pipelines from git repo yml
Home-page: https://bitbucket.org/fxquants/ae-agent/
Author: Jonathan Turnock
Author-email: jonathan.turnock@fxquants.net
License: MIT
Platform: UNKNOWN
Requires-Dist: docker
Requires-Dist: flask
Requires-Dist: fxq-core
Requires-Dist: gitpython
Requires-Dist: pyyaml
